sqlite_comprehend/__init__.py
sqlite_comprehend/__main__.py
sqlite_comprehend/cli.py
sqlite_comprehend/utils.py
sqlite_comprehend-0.2.2.dist-info/LICENSE
sqlite_comprehend-0.2.2.dist-info/METADATA
sqlite_comprehend-0.2.2.dist-info/WHEEL
sqlite_comprehend-0.2.2.dist-info/entry_points.txt
sqlite_comprehend-0.2.2.dist-info/top_level.txt
sqlite_comprehend-0.2.2.dist-info/RECORD
