Metadata-Version: 2.1
Name: sqlite-comprehend
Version: 0.2.2
Summary: Tools for running data in a SQLite database through AWS Comprehend
Home-page: https://github.com/simonw/sqlite-comprehend
Author: Simon Willison
License: Apache License, Version 2.0
Project-URL: Issues, https://github.com/simonw/sqlite-comprehend/issues
Project-URL: CI, https://github.com/simonw/sqlite-comprehend/actions
Project-URL: Changelog, https://github.com/simonw/sqlite-comprehend/releases
Requires-Python: >=3.7
License-File: LICENSE
Requires-Dist: click
Requires-Dist: boto3
Requires-Dist: sqlite-utils
Provides-Extra: test
Requires-Dist: pytest ; extra == 'test'
Requires-Dist: pytest-mock ; extra == 'test'
Requires-Dist: cogapp ; extra == 'test'
